main.py
bytekafka_0.0.15-98.7.dist-info/METADATA
bytekafka_0.0.15-98.7.dist-info/WHEEL
bytekafka_0.0.15-98.7.dist-info/top_level.txt
bytekafka_0.0.15-98.7.dist-info/RECORD
