Metadata-Version: 2.1
Name: bytekafka-0.0.15
Version: 98.7
Summary: x
Author: x
Author-email: xxx@outlook.com
Requires-Dist: requests
